compose_chart_export/__init__.py
compose_chart_export/chart_combiner.py
compose_chart_export/chart_export.py
compose_chart_export/chart_file_templates.py
compose_chart_export/chart_mods.py
compose_chart_export/chart_read.py
compose_chart_export/compose_export.py
compose_chart_export/ports.py
compose_chart_export/py.typed
compose_chart_export/settings.py
compose_chart_export-0.0.30.dist-info/METADATA
compose_chart_export-0.0.30.dist-info/WHEEL
compose_chart_export-0.0.30.dist-info/namespace_packages.txt
compose_chart_export-0.0.30.dist-info/top_level.txt
compose_chart_export-0.0.30.dist-info/RECORD
