Metadata-Version: 2.1
Name: compose-chart-export
Version: 0.0.30
Summary: compose_agent_export for docker-compose -> helm chart
Author: Espen Albert
License: MIT
Project-URL: Source, https://github.com/EspenAlbert/py-libs/tree/main/compose_chart_export
Project-URL: Documentation, https://espenalbert.github.io/py-libs/compose_chart_export
Classifier: Programming Language :: Python :: 3.9
Classifier: Programming Language :: Python :: 3.10
Classifier: Programming Language :: Python :: 3.11
Classifier: Development Status :: 3 - Alpha
Requires-Python: >=3.9
Requires-Dist: docker-compose-parser (==v0.0.30)
Requires-Dist: model-lib (==v0.0.30)
Requires-Dist: pydantic (<3,>=1.10.2)
Requires-Dist: semver (==2.13.0)
Requires-Dist: typing-extensions (>=4.3.0)
Requires-Dist: zero-3rdparty (==v0.0.30)
Provides-Extra: pydantic_v1
Requires-Dist: pydantic (<=2,>=1.10.2) ; extra == 'pydantic_v1'
Provides-Extra: pydantic_v2
Requires-Dist: pydantic (<=3,>=2.1.1) ; extra == 'pydantic_v2'
Requires-Dist: pydantic-settings (>=2.0.3) ; extra == 'pydantic_v2'
